{
  "version": "7",
  "dialect": "postgresql",
  "entries": [
    {
      "idx": 0,
      "version": "7",
      "when": 1772737100141,
      "tag": "0000_zippy_hydra",
      "breakpoints": true
    },
    {
      "idx": 1,
      "version": "7",
      "when": 1772744747170,
      "tag": "0001_talented_longshot",
      "breakpoints": true
    },
    {
      "idx": 2,
      "version": "7",
      "when": 1772757555278,
      "tag": "0002_condemned_gideon",
      "breakpoints": true
    },
    {
      "idx": 3,
      "version": "7",
      "when": 1772790993735,
      "tag": "0003_premium_emma_frost",
      "breakpoints": true
    },
    {
      "idx": 4,
      "version": "7",
      "when": 1772792021696,
      "tag": "0004_broken_darkstar",
      "breakpoints": true
    },
    {
      "idx": 5,
      "version": "7",
      "when": 1772793331636,
      "tag": "0005_sudden_garia",
      "breakpoints": true
    }
  ]
}